Metadata-Version: 1.0
Name: pckByHM
Version: 1.0
Summary: Gaussian and Binomial distributions
Home-page: UNKNOWN
Author: Harshit Malhotra
Author-email: 18ucs207@lnmiit.ac.in
License: UNKNOWN
Platform: UNKNOWN
